netlink/applog/__init__.py
netlink/applog/application_log.py
netlink_applog-0.0.2.dist-info/WHEEL
netlink_applog-0.0.2.dist-info/METADATA
netlink_applog-0.0.2.dist-info/RECORD
